MANIFEST.in
README.txt
setup.py
functions/__init__.py
wmc_datalake_functions.egg-info/PKG-INFO
wmc_datalake_functions.egg-info/SOURCES.txt
wmc_datalake_functions.egg-info/dependency_links.txt
wmc_datalake_functions.egg-info/top_level.txt