Metadata-Version: 1.1
Name: wmc-datalake-functions
Version: 1.0
Summary: Functions from WMC Datalake
Home-page: UNKNOWN
Author: Daniel Santhiago
Author-email: UNKNOWN
License: MIT
Platform: UNKNOWN
Classifier: Development Status :: 5 - Production/Stable
Classifier: Intended Audience :: Developers
Classifier: Operating System :: Microsoft :: Windows :: Windows 10
Classifier: License :: OSI Approved :: MIT License
Classifier: Programming Language :: Python :: 3
